{"targets":[{"isStage":true,"name":"Stage","variables":{"`jEk@4|i[#Fk?(8x)AV.-my variable":["my variable",0]},"lists":{},"broadcasts":{},"blocks":{},"comments":{},"currentCostume":1,"costumes":[{"assetId":"cd21514d0531fdffb22204e0ec5ed84a","name":"backdrop1","md5ext":"cd21514d0531fdffb22204e0ec5ed84a.svg","dataFormat":"svg","rotationCenterX":240,"rotationCenterY":180},{"assetId":"a5865738283613a2725b2c9dda6d8c78","name":"Basketball 2","bitmapResolution":2,"md5ext":"a5865738283613a2725b2c9dda6d8c78.png","dataFormat":"png","rotationCenterX":480,"rotationCenterY":360}],"sounds":[{"assetId":"83a9787d4cb6f3b7632b4ddfebf74367","name":"pop","dataFormat":"wav","format":"","rate":44100,"sampleCount":1032,"md5ext":"83a9787d4cb6f3b7632b4ddfebf74367.wav"}],"volume":100,"layerOrder":0,"tempo":60,"videoTransparency":50,"videoState":"on","textToSpeechLanguage":null},{"isStage":false,"name":"Glow-L","variables":{},"lists":{},"broadcasts":{},"blocks":{"2ZeSjrY.q2K[mTn9jNRh":{"opcode":"motion_gotoxy","next":"DKLnh_PTj4-^qVT_f;Nb","parent":"~`L[k[4Si9DC;T34`k%l","inputs":{"X":[1,[4,"-169"]],"Y":[1,[4,"23"]]},"fields":{},"shadow":false,"topLevel":false},"DKLnh_PTj4-^qVT_f;Nb":{"opcode":"looks_changeeffectby","next":null,"parent":"2ZeSjrY.q2K[mTn9jNRh","inputs":{"CHANGE":[1,[4,"50"]]},"fields":{"EFFECT":["COLOR",null]},"shadow":false,"topLevel":false},"~`L[k[4Si9DC;T34`k%l":{"opcode":"event_whenthisspriteclicked","next":"2ZeSjrY.q2K[mTn9jNRh","parent":null,"inputs":{},"fields":{},"shadow":false,"topLevel":true,"x":22,"y":120},"6qPr~i{qLC.H8|/B$oRz":{"opcode":"event_whenkeypressed","next":"3jM-Lh0i)*1Fu[Ebcn;J","parent":null,"inputs":{},"fields":{"KEY_OPTION":["space",null]},"shadow":false,"topLevel":true,"x":394,"y":139},"3jM-Lh0i)*1Fu[Ebcn;J":{"opcode":"motion_goto","next":null,"parent":"6qPr~i{qLC.H8|/B$oRz","inputs":{"TO":[1,"=20S6:${xvN/xp09.g8!"]},"fields":{},"shadow":false,"topLevel":false},"=20S6:${xvN/xp09.g8!":{"opcode":"motion_goto_menu","next":null,"parent":"3jM-Lh0i)*1Fu[Ebcn;J","inputs":{},"fields":{"TO":["_random_",null]},"shadow":true,"topLevel":false}},"comments":{},"currentCostume":0,"costumes":[{"assetId":"dcee9202cf20e0395971f1ee73c45d37","name":"Glow-L","bitmapResolution":1,"md5ext":"dcee9202cf20e0395971f1ee73c45d37.svg","dataFormat":"svg","rotationCenterX":33,"rotationCenterY":35}],"sounds":[{"assetId":"83a9787d4cb6f3b7632b4ddfebf74367","name":"pop","dataFormat":"wav","format":"","rate":44100,"sampleCount":1032,"md5ext":"83a9787d4cb6f3b7632b4ddfebf74367.wav"}],"volume":100,"layerOrder":1,"visible":true,"x":-169,"y":23,"size":100,"direction":90,"draggable":false,"rotationStyle":"all around"},{"isStage":false,"name":"Glow-A","variables":{},"lists":{},"broadcasts":{},"blocks":{"j)qCye}qt8[#]cDMzFIg":{"opcode":"motion_gotoxy","next":"P;-r(]n?nfqe(_4jO(:I","parent":"a|OCwZ0?4.B#](`Q;t[!","inputs":{"X":[1,[4,"-88"]],"Y":[1,[4,"17"]]},"fields":{},"shadow":false,"topLevel":false},"P;-r(]n?nfqe(_4jO(:I":{"opcode":"looks_changeeffectby","next":null,"parent":"j)qCye}qt8[#]cDMzFIg","inputs":{"CHANGE":[1,[4,"25"]]},"fields":{"EFFECT":["COLOR",null]},"shadow":false,"topLevel":false},"a|OCwZ0?4.B#](`Q;t[!":{"opcode":"event_whenthisspriteclicked","next":"j)qCye}qt8[#]cDMzFIg","parent":null,"inputs":{},"fields":{},"shadow":false,"topLevel":true,"x":62,"y":139},"RKad-)OsfyQuFKhd.PV7":{"opcode":"event_whenkeypressed","next":"D4or50N*Kxk[DBr~dUkR","parent":null,"inputs":{},"fields":{"KEY_OPTION":["space",null]},"shadow":false,"topLevel":true,"x":453,"y":76},"D4or50N*Kxk[DBr~dUkR":{"opcode":"motion_goto","next":null,"parent":"RKad-)OsfyQuFKhd.PV7","inputs":{"TO":[1,"Q/vPSbpV$f{dHpC11E@h"]},"fields":{},"shadow":false,"topLevel":false},"Q/vPSbpV$f{dHpC11E@h":{"opcode":"motion_goto_menu","next":null,"parent":"D4or50N*Kxk[DBr~dUkR","inputs":{},"fields":{"TO":["_random_",null]},"shadow":true,"topLevel":false}},"comments":{},"currentCostume":0,"costumes":[{"assetId":"fd470938cce54248aaf240b16e845456","name":"Glow-A","bitmapResolution":1,"md5ext":"fd470938cce54248aaf240b16e845456.svg","dataFormat":"svg","rotationCenterX":36,"rotationCenterY":37}],"sounds":[{"assetId":"83a9787d4cb6f3b7632b4ddfebf74367","name":"pop","dataFormat":"wav","format":"","rate":44100,"sampleCount":1032,"md5ext":"83a9787d4cb6f3b7632b4ddfebf74367.wav"}],"volume":100,"layerOrder":2,"visible":true,"x":-88,"y":17,"size":100,"direction":90,"draggable":false,"rotationStyle":"all around"},{"isStage":false,"name":"Glow-U","variables":{},"lists":{},"broadcasts":{},"blocks":{"SzAoLL0gep6tywEzZ:%p":{"opcode":"event_whenthisspriteclicked","next":"y8I}V2$XJrIi{vUkb9@p","parent":null,"inputs":{},"fields":{},"shadow":false,"topLevel":true,"x":275,"y":138},"y8I}V2$XJrIi{vUkb9@p":{"opcode":"motion_gotoxy","next":"sy|+OprN1V;XF;aG1`94","parent":"SzAoLL0gep6tywEzZ:%p","inputs":{"X":[1,[4,"-18"]],"Y":[1,[4,"23"]]},"fields":{},"shadow":false,"topLevel":false},"sy|+OprN1V;XF;aG1`94":{"opcode":"looks_changeeffectby","next":"Ry6=Iq^1c,gEeJCtvLr`","parent":"y8I}V2$XJrIi{vUkb9@p","inputs":{"CHANGE":[1,[4,"10"]]},"fields":{"EFFECT":["COLOR",null]},"shadow":false,"topLevel":false},"Ry6=Iq^1c,gEeJCtvLr`":{"opcode":"sound_playuntildone","next":null,"parent":"sy|+OprN1V;XF;aG1`94","inputs":{"SOUND_MENU":[1,"}nU+=hwC4EmaCJ{./Hdm"]},"fields":{},"shadow":false,"topLevel":false},"}nU+=hwC4EmaCJ{./Hdm":{"opcode":"sound_sounds_menu","next":null,"parent":"Ry6=Iq^1c,gEeJCtvLr`","inputs":{},"fields":{"SOUND_MENU":["pop",null]},"shadow":true,"topLevel":false},"]q`k8v*soto9#sil}6r#":{"opcode":"event_whenkeypressed","next":"9dIy.7!tUDi]`O?B|(0U","parent":null,"inputs":{},"fields":{"KEY_OPTION":["space",null]},"shadow":false,"topLevel":true,"x":659,"y":123},"9dIy.7!tUDi]`O?B|(0U":{"opcode":"motion_goto","next":null,"parent":"]q`k8v*soto9#sil}6r#","inputs":{"TO":[1,"G}QlxAY8wc0r)wPhLf)}"]},"fields":{},"shadow":false,"topLevel":false},"G}QlxAY8wc0r)wPhLf)}":{"opcode":"motion_goto_menu","next":null,"parent":"9dIy.7!tUDi]`O?B|(0U","inputs":{},"fields":{"TO":["_random_",null]},"shadow":true,"topLevel":false}},"comments":{},"currentCostume":0,"costumes":[{"assetId":"cb8ef2244400a57ba08e918cb4fe8bba","name":"Glow-U","bitmapResolution":1,"md5ext":"cb8ef2244400a57ba08e918cb4fe8bba.svg","dataFormat":"svg","rotationCenterX":37,"rotationCenterY":37}],"sounds":[{"assetId":"83a9787d4cb6f3b7632b4ddfebf74367","name":"pop","dataFormat":"wav","format":"","rate":44100,"sampleCount":1032,"md5ext":"83a9787d4cb6f3b7632b4ddfebf74367.wav"}],"volume":100,"layerOrder":3,"visible":true,"x":-18,"y":23,"size":100,"direction":90,"draggable":false,"rotationStyle":"all around"},{"isStage":false,"name":"Glow-R","variables":{},"lists":{},"broadcasts":{},"blocks":{"rk^3H3GiVtV$}E(60VxU":{"opcode":"event_whenthisspriteclicked","next":"!Y7ltvArpcN-3(f8D}Va","parent":null,"inputs":{},"fields":{},"shadow":false,"topLevel":true,"x":121,"y":138},"!Y7ltvArpcN-3(f8D}Va":{"opcode":"motion_gotoxy","next":"pdOkuiUE]nE8W!di6+DT","parent":"rk^3H3GiVtV$}E(60VxU","inputs":{"X":[1,[4,"60"]],"Y":[1,[4,"18"]]},"fields":{},"shadow":false,"topLevel":false},"pdOkuiUE]nE8W!di6+DT":{"opcode":"looks_changeeffectby","next":null,"parent":"!Y7ltvArpcN-3(f8D}Va","inputs":{"CHANGE":[1,[4,"70"]]},"fields":{"EFFECT":["COLOR",null]},"shadow":false,"topLevel":false},"eN@YIrMVkgv,pTCJzgw[":{"opcode":"event_whenflagclicked","next":"ei5o4)i0DX,FO,!mNh17","parent":null,"inputs":{},"fields":{},"shadow":false,"topLevel":true,"x":476,"y":69},"5d@abbQf/-Y1-DoNM;]|":{"opcode":"event_whenkeypressed","next":"OwpR?[Mk`$ZPK$z*mMz)","parent":null,"inputs":{},"fields":{"KEY_OPTION":["space",null]},"shadow":false,"topLevel":true,"x":253,"y":470},"OwpR?[Mk`$ZPK$z*mMz)":{"opcode":"motion_goto","next":null,"parent":"5d@abbQf/-Y1-DoNM;]|","inputs":{"TO":[1,"RC^]Kv9hwsqVM9.y!qJg"]},"fields":{},"shadow":false,"topLevel":false},"RC^]Kv9hwsqVM9.y!qJg":{"opcode":"motion_goto_menu","next":null,"parent":"OwpR?[Mk`$ZPK$z*mMz)","inputs":{},"fields":{"TO":["_random_",null]},"shadow":true,"topLevel":false},"ei5o4)i0DX,FO,!mNh17":{"opcode":"control_repeat","next":null,"parent":"eN@YIrMVkgv,pTCJzgw[","inputs":{"TIMES":[1,[6,"10"]],"SUBSTACK":[2,"kLxL8aIw/*LU[xmNzHEs"]},"fields":{},"shadow":false,"topLevel":false},"kLxL8aIw/*LU[xmNzHEs":{"opcode":"motion_turnright","next":null,"parent":"ei5o4)i0DX,FO,!mNh17","inputs":{"DEGREES":[1,[4,"45"]]},"fields":{},"shadow":false,"topLevel":false}},"comments":{},"currentCostume":0,"costumes":[{"assetId":"bb11b49e19c68452331e78d51081ab42","name":"Glow-R","bitmapResolution":1,"md5ext":"bb11b49e19c68452331e78d51081ab42.svg","dataFormat":"svg","rotationCenterX":35,"rotationCenterY":38}],"sounds":[{"assetId":"83a9787d4cb6f3b7632b4ddfebf74367","name":"pop","dataFormat":"wav","format":"","rate":44100,"sampleCount":1032,"md5ext":"83a9787d4cb6f3b7632b4ddfebf74367.wav"}],"volume":100,"layerOrder":4,"visible":true,"x":60,"y":18,"size":100,"direction":180,"draggable":false,"rotationStyle":"all around"},{"isStage":false,"name":"Glow-E","variables":{},"lists":{},"broadcasts":{},"blocks":{"[7!ZAi9{:`1(6{7a8E~_":{"opcode":"event_whenthisspriteclicked","next":"!9_J2%Z]v,tw?A/!HcR4","parent":null,"inputs":{},"fields":{},"shadow":false,"topLevel":true,"x":108,"y":114},"!9_J2%Z]v,tw?A/!HcR4":{"opcode":"motion_gotoxy","next":"gzP!Q=w2L_qRTv.5^^Lv","parent":"[7!ZAi9{:`1(6{7a8E~_","inputs":{"X":[1,[4,"129"]],"Y":[1,[4,"22"]]},"fields":{},"shadow":false,"topLevel":false},"gzP!Q=w2L_qRTv.5^^Lv":{"opcode":"looks_sayforsecs","next":"Q#T6;3e2`}#QE!)}p_3.","parent":"!9_J2%Z]v,tw?A/!HcR4","inputs":{"MESSAGE":[1,[10,"Hello!"]],"SECS":[1,[4,"2"]]},"fields":{},"shadow":false,"topLevel":false},"Q#T6;3e2`}#QE!)}p_3.":{"opcode":"looks_changeeffectby","next":null,"parent":"gzP!Q=w2L_qRTv.5^^Lv","inputs":{"CHANGE":[1,[4,"35"]]},"fields":{"EFFECT":["COLOR",null]},"shadow":false,"topLevel":false},"-eXkBj$Nv*oo+P2*=C{i":{"opcode":"event_whenflagclicked","next":"5C$RWZ,E0jM6KwIyIv31","parent":null,"inputs":{},"fields":{},"shadow":false,"topLevel":true,"x":529,"y":158},"Pfj}!yh9;|w9CH$e~TA?":{"opcode":"motion_turnright","next":null,"parent":"5C$RWZ,E0jM6KwIyIv31","inputs":{"DEGREES":[1,[4,"90"]]},"fields":{},"shadow":false,"topLevel":false},"5C$RWZ,E0jM6KwIyIv31":{"opcode":"control_repeat","next":null,"parent":"-eXkBj$Nv*oo+P2*=C{i","inputs":{"TIMES":[1,[6,"10"]],"SUBSTACK":[2,"Pfj}!yh9;|w9CH$e~TA?"]},"fields":{},"shadow":false,"topLevel":false},"#(U0OQ64VqzL6CB_.zgY":{"opcode":"event_whenkeypressed","next":"ZHfjiY!d;$$+GIp=r7MX","parent":null,"inputs":{},"fields":{"KEY_OPTION":["space",null]},"shadow":false,"topLevel":true,"x":129,"y":522},"ZHfjiY!d;$$+GIp=r7MX":{"opcode":"motion_goto","next":null,"parent":"#(U0OQ64VqzL6CB_.zgY","inputs":{"TO":[1,"8L]ty(!?A$hT?;3C7K2["]},"fields":{},"shadow":false,"topLevel":false},"8L]ty(!?A$hT?;3C7K2[":{"opcode":"motion_goto_menu","next":null,"parent":"ZHfjiY!d;$$+GIp=r7MX","inputs":{},"fields":{"TO":["_random_",null]},"shadow":true,"topLevel":false}},"comments":{},"currentCostume":0,"costumes":[{"assetId":"80382a5db3fa556276068165c547b432","name":"Glow-E","bitmapResolution":1,"md5ext":"80382a5db3fa556276068165c547b432.svg","dataFormat":"svg","rotationCenterX":34,"rotationCenterY":38}],"sounds":[{"assetId":"83a9787d4cb6f3b7632b4ddfebf74367","name":"pop","dataFormat":"wav","format":"","rate":44100,"sampleCount":1032,"md5ext":"83a9787d4cb6f3b7632b4ddfebf74367.wav"}],"volume":100,"layerOrder":5,"visible":true,"x":129,"y":22,"size":100,"direction":60,"draggable":false,"rotationStyle":"all around"},{"isStage":false,"name":"Glow-N","variables":{},"lists":{},"broadcasts":{},"blocks":{"uKJ0vjw_|hF6o[W)TV=T":{"opcode":"event_whenthisspriteclicked","next":"Decf?_;ZQ?BFl{h62b_@","parent":null,"inputs":{},"fields":{},"shadow":false,"topLevel":true,"x":188,"y":126},"Decf?_;ZQ?BFl{h62b_@":{"opcode":"motion_gotoxy","next":"XIiQ}L(b^T+tf]9,~!^M","parent":"uKJ0vjw_|hF6o[W)TV=T","inputs":{"X":[1,[4,"203"]],"Y":[1,[4,"21"]]},"fields":{},"shadow":false,"topLevel":false},"XIiQ}L(b^T+tf]9,~!^M":{"opcode":"looks_changeeffectby","next":null,"parent":"Decf?_;ZQ?BFl{h62b_@","inputs":{"CHANGE":[1,[4,"80"]]},"fields":{"EFFECT":["COLOR",null]},"shadow":false,"topLevel":false},"4YJ@%7{pBA~#@SV$]r1[":{"opcode":"motion_turnright","next":null,"parent":"M$[a|R!UPwyF?FG^:r$$","inputs":{"DEGREES":[1,[4,"90"]]},"fields":{},"shadow":false,"topLevel":false},"M$[a|R!UPwyF?FG^:r$$":{"opcode":"event_whenflagclicked","next":"4YJ@%7{pBA~#@SV$]r1[","parent":null,"inputs":{},"fields":{},"shadow":false,"topLevel":true,"x":619,"y":50}},"comments":{},"currentCostume":0,"costumes":[{"assetId":"d55a04ada14958eccc4aef446a4dad57","name":"Glow-N","bitmapResolution":1,"md5ext":"d55a04ada14958eccc4aef446a4dad57.svg","dataFormat":"svg","rotationCenterX":37,"rotationCenterY":39}],"sounds":[{"assetId":"83a9787d4cb6f3b7632b4ddfebf74367","name":"pop","dataFormat":"wav","format":"","rate":44100,"sampleCount":1032,"md5ext":"83a9787d4cb6f3b7632b4ddfebf74367.wav"}],"volume":100,"layerOrder":6,"visible":true,"x":203,"y":21,"size":100,"direction":180,"draggable":false,"rotationStyle":"all around"}],"monitors":[],"extensions":[],"meta":{"semver":"3.0.0","vm":"0.2.0-prerelease.20200527195112","agent":"Mozilla/5.0 (Macintosh; Intel Mac OS X 10_15_4) AppleWebKit/537.36 (KHTML, like Gecko) Chrome/81.0.4044.138 Safari/537.36"}}