{"targets":[{"isStage":true,"name":"Stage","variables":{"`jEk@4|i[#Fk?(8x)AV.-my variable":["my variable","0"],"##/x16]_2!:FArb)VK6j":["Score",1]},"lists":{},"broadcasts":{},"blocks":{},"comments":{},"currentCostume":1,"costumes":[{"assetId":"cd21514d0531fdffb22204e0ec5ed84a","name":"backdrop1","md5ext":"cd21514d0531fdffb22204e0ec5ed84a.svg","dataFormat":"svg","rotationCenterX":240,"rotationCenterY":180},{"assetId":"47282ff0f7047c6fab9c94b531abf721","name":"Stars","bitmapResolution":2,"md5ext":"47282ff0f7047c6fab9c94b531abf721.png","dataFormat":"png","rotationCenterX":480,"rotationCenterY":360}],"sounds":[{"assetId":"83a9787d4cb6f3b7632b4ddfebf74367","name":"pop","dataFormat":"wav","format":"","rate":48000,"sampleCount":1123,"md5ext":"83a9787d4cb6f3b7632b4ddfebf74367.wav"}],"volume":100,"layerOrder":0,"tempo":60,"videoTransparency":50,"videoState":"on","textToSpeechLanguage":null},{"isStage":false,"name":"Ball","variables":{},"lists":{},"broadcasts":{},"blocks":{"S{!U73prMJ)Q`_|oG%Ae":{"opcode":"event_whenflagclicked","next":"r!-YqF+0tR5;8$4?Vg_K","parent":null,"inputs":{},"fields":{},"shadow":false,"topLevel":true,"x":93,"y":-100},"r!-YqF+0tR5;8$4?Vg_K":{"opcode":"motion_pointindirection","next":"H?ZXwJkNyW?Rp#e=e+]!","parent":"S{!U73prMJ)Q`_|oG%Ae","inputs":{"DIRECTION":[1,[8,"45"]]},"fields":{},"shadow":false,"topLevel":false},"H?ZXwJkNyW?Rp#e=e+]!":{"opcode":"control_forever","next":null,"parent":"r!-YqF+0tR5;8$4?Vg_K","inputs":{"SUBSTACK":[2,"4tKUij9T)[0m4_-]$HX4"]},"fields":{},"shadow":false,"topLevel":false},"4tKUij9T)[0m4_-]$HX4":{"opcode":"motion_movesteps","next":"+dM:}ya^p:VhDyS_oNF;","parent":"H?ZXwJkNyW?Rp#e=e+]!","inputs":{"STEPS":[1,[4,"15"]]},"fields":{},"shadow":false,"topLevel":false},"+dM:}ya^p:VhDyS_oNF;":{"opcode":"motion_ifonedgebounce","next":null,"parent":"4tKUij9T)[0m4_-]$HX4","inputs":{},"fields":{},"shadow":false,"topLevel":false},"CxRMo:bt:::d28/CK;9S":{"opcode":"control_if","next":null,"parent":"fjmXKCX?cCaj,3@K`A;#","inputs":{"CONDITION":[2,"d`,vG}r!HJ(sd$vC+WNv"],"SUBSTACK":[2,"$iAlu2g*K,nR)]6py~(:"]},"fields":{},"shadow":false,"topLevel":false},"d`,vG}r!HJ(sd$vC+WNv":{"opcode":"sensing_touchingobject","next":null,"parent":"CxRMo:bt:::d28/CK;9S","inputs":{"TOUCHINGOBJECTMENU":[1,"4tf8e}[V.DSMH[jBQW9/"]},"fields":{},"shadow":false,"topLevel":false},"4tf8e}[V.DSMH[jBQW9/":{"opcode":"sensing_touchingobjectmenu","next":null,"parent":"d`,vG}r!HJ(sd$vC+WNv","inputs":{},"fields":{"TOUCHINGOBJECTMENU":["Paddle",null]},"shadow":true,"topLevel":false},"}|Gy09,D2Y*Mj2F5F(rs":{"opcode":"motion_turnright","next":"A0;O:JAi;kK]{$|=b}1/","parent":"$iAlu2g*K,nR)]6py~(:","inputs":{"DEGREES":[1,[4,"180"]]},"fields":{},"shadow":false,"topLevel":false},"A0;O:JAi;kK]{$|=b}1/":{"opcode":"motion_movesteps","next":"3V5e4.^58c.3e~Qm1/%V","parent":"}|Gy09,D2Y*Mj2F5F(rs","inputs":{"STEPS":[1,[4,"15"]]},"fields":{},"shadow":false,"topLevel":false},"fjmXKCX?cCaj,3@K`A;#":{"opcode":"control_forever","next":null,"parent":"ijQR_TeVixb1j)28t?:4","inputs":{"SUBSTACK":[2,"CxRMo:bt:::d28/CK;9S"]},"fields":{},"shadow":false,"topLevel":false},"3V5e4.^58c.3e~Qm1/%V":{"opcode":"control_wait","next":null,"parent":"A0;O:JAi;kK]{$|=b}1/","inputs":{"DURATION":[1,[5,"0.5"]]},"fields":{},"shadow":false,"topLevel":false},"ijQR_TeVixb1j)28t?:4":{"opcode":"event_whenflagclicked","next":"fjmXKCX?cCaj,3@K`A;#","parent":null,"inputs":{},"fields":{},"shadow":false,"topLevel":true,"x":337,"y":-127},"$iAlu2g*K,nR)]6py~(:":{"opcode":"data_changevariableby","next":"}|Gy09,D2Y*Mj2F5F(rs","parent":"CxRMo:bt:::d28/CK;9S","inputs":{"VALUE":[1,[4,"1"]]},"fields":{"VARIABLE":["Score","##/x16]_2!:FArb)VK6j"]},"shadow":false,"topLevel":false},"zew8ZK0d=Sh0)f]fhTs7":{"opcode":"event_whenflagclicked","next":"H^d}1.~XHT,|*gLxh@O^","parent":null,"inputs":{},"fields":{},"shadow":false,"topLevel":true,"x":714,"y":174},"H^d}1.~XHT,|*gLxh@O^":{"opcode":"data_setvariableto","next":null,"parent":"zew8ZK0d=Sh0)f]fhTs7","inputs":{"VALUE":[1,[10,"0"]]},"fields":{"VARIABLE":["Score","##/x16]_2!:FArb)VK6j"]},"shadow":false,"topLevel":false}},"comments":{},"currentCostume":0,"costumes":[{"assetId":"3c6241985b581284ec191f9d1deffde8","name":"ball-a","bitmapResolution":1,"md5ext":"3c6241985b581284ec191f9d1deffde8.svg","dataFormat":"svg","rotationCenterX":22,"rotationCenterY":22},{"assetId":"ad7dc51cafd73e8279073e33b0eab335","name":"ball-b","bitmapResolution":1,"md5ext":"ad7dc51cafd73e8279073e33b0eab335.svg","dataFormat":"svg","rotationCenterX":22,"rotationCenterY":22},{"assetId":"f221a2edf87aff3615c0c003e616b31b","name":"ball-c","bitmapResolution":1,"md5ext":"f221a2edf87aff3615c0c003e616b31b.svg","dataFormat":"svg","rotationCenterX":22,"rotationCenterY":22},{"assetId":"db144b2a19f4f1ab31e30d58f00447dc","name":"ball-d","bitmapResolution":1,"md5ext":"db144b2a19f4f1ab31e30d58f00447dc.svg","dataFormat":"svg","rotationCenterX":22,"rotationCenterY":22},{"assetId":"1c44b7494dec047371f74c705f1d99fc","name":"ball-e","bitmapResolution":1,"md5ext":"1c44b7494dec047371f74c705f1d99fc.svg","dataFormat":"svg","rotationCenterX":22,"rotationCenterY":22}],"sounds":[{"assetId":"53a3c2e27d1fb5fdb14aaf0cb41e7889","name":"Boing","dataFormat":"wav","format":"adpcm","rate":22050,"sampleCount":7113,"md5ext":"53a3c2e27d1fb5fdb14aaf0cb41e7889.wav"},{"assetId":"83a9787d4cb6f3b7632b4ddfebf74367","name":"Pop","dataFormat":"wav","format":"","rate":48000,"sampleCount":1123,"md5ext":"83a9787d4cb6f3b7632b4ddfebf74367.wav"}],"volume":100,"layerOrder":1,"visible":true,"x":-26.18583684619876,"y":-23.004058859571323,"size":100,"direction":-135,"draggable":false,"rotationStyle":"all around"},{"isStage":false,"name":"Paddle","variables":{},"lists":{},"broadcasts":{},"blocks":{":`r]Y9KO`K8))M+hth[;":{"opcode":"motion_setx","next":null,"parent":"vI61Jw6/Q`FG)3?Bqay-","inputs":{"X":[3,"d3U58M/3H)l6`2.?)1B{",[4,"17"]]},"fields":{},"shadow":false,"topLevel":false},"d3U58M/3H)l6`2.?)1B{":{"opcode":"sensing_mousex","next":null,"parent":":`r]Y9KO`K8))M+hth[;","inputs":{},"fields":{},"shadow":false,"topLevel":false},"vI61Jw6/Q`FG)3?Bqay-":{"opcode":"control_forever","next":null,"parent":"Ub52.B7V$`+eu6A2Swo|","inputs":{"SUBSTACK":[2,":`r]Y9KO`K8))M+hth[;"]},"fields":{},"shadow":false,"topLevel":false},"Ub52.B7V$`+eu6A2Swo|":{"opcode":"event_whenflagclicked","next":"vI61Jw6/Q`FG)3?Bqay-","parent":null,"inputs":{},"fields":{},"shadow":false,"topLevel":true,"x":409,"y":71}},"comments":{},"currentCostume":0,"costumes":[{"assetId":"15864fac7d38bb94c1ec3a199de96c26","name":"paddle","bitmapResolution":1,"md5ext":"15864fac7d38bb94c1ec3a199de96c26.svg","dataFormat":"svg","rotationCenterX":44,"rotationCenterY":7}],"sounds":[{"assetId":"53a3c2e27d1fb5fdb14aaf0cb41e7889","name":"boing","dataFormat":"wav","format":"adpcm","rate":22050,"sampleCount":7113,"md5ext":"53a3c2e27d1fb5fdb14aaf0cb41e7889.wav"}],"volume":100,"layerOrder":2,"visible":true,"x":-188,"y":-124,"size":100,"direction":90,"draggable":false,"rotationStyle":"all around"},{"isStage":false,"name":"Line","variables":{},"lists":{},"broadcasts":{},"blocks":{"5%-mu~p6AhU7DCu]ZW[;":{"opcode":"event_whenflagclicked","next":"Dk7O[OKquG4SaI8IokRq","parent":null,"inputs":{},"fields":{},"shadow":false,"topLevel":true,"x":293,"y":52},"Dk7O[OKquG4SaI8IokRq":{"opcode":"control_forever","next":null,"parent":"5%-mu~p6AhU7DCu]ZW[;","inputs":{"SUBSTACK":[2,"jtGM`8@sS/ALe~{UkAr0"]},"fields":{},"shadow":false,"topLevel":false},"jtGM`8@sS/ALe~{UkAr0":{"opcode":"control_if","next":null,"parent":"Dk7O[OKquG4SaI8IokRq","inputs":{"CONDITION":[2,"^e7T:rKD7oCP|a[!:BN5"],"SUBSTACK":[2,";_Hk#XWu]h6QO.b|gKAe"]},"fields":{},"shadow":false,"topLevel":false},"^e7T:rKD7oCP|a[!:BN5":{"opcode":"sensing_touchingobject","next":null,"parent":"jtGM`8@sS/ALe~{UkAr0","inputs":{"TOUCHINGOBJECTMENU":[1,"/p!QNX{B%Q.MQK+WgLFw"]},"fields":{},"shadow":false,"topLevel":false},"/p!QNX{B%Q.MQK+WgLFw":{"opcode":"sensing_touchingobjectmenu","next":null,"parent":"^e7T:rKD7oCP|a[!:BN5","inputs":{},"fields":{"TOUCHINGOBJECTMENU":["Ball",null]},"shadow":true,"topLevel":false},";_Hk#XWu]h6QO.b|gKAe":{"opcode":"control_stop","next":null,"parent":"jtGM`8@sS/ALe~{UkAr0","inputs":{},"fields":{"STOP_OPTION":["all",null]},"shadow":false,"topLevel":false,"mutation":{"tagName":"mutation","children":[],"hasnext":"false"}}},"comments":{},"currentCostume":0,"costumes":[{"assetId":"e85305b47cfd92d971704dcb7ad6e17b","name":"line","bitmapResolution":1,"md5ext":"e85305b47cfd92d971704dcb7ad6e17b.svg","dataFormat":"svg","rotationCenterX":239,"rotationCenterY":7}],"sounds":[{"assetId":"83a9787d4cb6f3b7632b4ddfebf74367","name":"pop","dataFormat":"wav","format":"","rate":48000,"sampleCount":1123,"md5ext":"83a9787d4cb6f3b7632b4ddfebf74367.wav"}],"volume":100,"layerOrder":3,"visible":true,"x":-1,"y":-177,"size":100,"direction":90,"draggable":false,"rotationStyle":"all around"}],"monitors":[{"id":"##/x16]_2!:FArb)VK6j","mode":"default","opcode":"data_variable","params":{"VARIABLE":"Score"},"spriteName":null,"value":1,"width":0,"height":0,"x":5,"y":5,"visible":true,"sliderMin":0,"sliderMax":100,"isDiscrete":true}],"extensions":[],"meta":{"semver":"3.0.0","vm":"0.2.0-prerelease.20210324111836","agent":"Mozilla/5.0 (X11; CrOS x86_64 13729.72.0) AppleWebKit/537.36 (KHTML, like Gecko) Chrome/89.0.4389.116 Safari/537.36"}}